odoo/addons/mis_builder_operating_unit/README.rst
odoo/addons/mis_builder_operating_unit/__init__.py
odoo/addons/mis_builder_operating_unit/__manifest__.py
odoo/addons/mis_builder_operating_unit/model/__init__.py
odoo/addons/mis_builder_operating_unit/model/mis_builder.py
odoo/addons/mis_builder_operating_unit/readme/CONTRIBUTORS.rst
odoo/addons/mis_builder_operating_unit/readme/DESCRIPTION.rst
odoo/addons/mis_builder_operating_unit/readme/USAGE.rst
odoo/addons/mis_builder_operating_unit/security/mis_builder_security.xml
odoo/addons/mis_builder_operating_unit/static/description/icon.png
odoo/addons/mis_builder_operating_unit/static/description/index.html
odoo/addons/mis_builder_operating_unit/view/mis_builder.xml
odoo11_addon_mis_builder_operating_unit-11.0.1.0.0.99.dev3.dist-info/METADATA
odoo11_addon_mis_builder_operating_unit-11.0.1.0.0.99.dev3.dist-info/WHEEL
odoo11_addon_mis_builder_operating_unit-11.0.1.0.0.99.dev3.dist-info/top_level.txt
odoo11_addon_mis_builder_operating_unit-11.0.1.0.0.99.dev3.dist-info/RECORD
